timenow/__init__.py
timenow/cli.py
timenow_cli-1.0.2.dist-info/licenses/LICENSE
timenow_cli-1.0.2.dist-info/METADATA
timenow_cli-1.0.2.dist-info/WHEEL
timenow_cli-1.0.2.dist-info/entry_points.txt
timenow_cli-1.0.2.dist-info/top_level.txt
timenow_cli-1.0.2.dist-info/RECORD
