Metadata-Version: 2.4
Name: timenow-cli
Version: 1.0.2
Summary: A simple CLI to get the current time in any city worldwide.
Author-email: Ninza Panda <ninzaapanda@gmail.com>
License: MIT
Project-URL: Homepage, https://github.com/yourusername/timenow-cli
Project-URL: Repository, https://github.com/yourusername/timenow-cli
Requires-Python: >=3.7
License-File: LICENSE
Requires-Dist: requests
Requires-Dist: pytz
Dynamic: license-file
